adls_management/__init__.py
adls_management/adls_management/__init__.py
adls_management/adls_management/connection.py
adls_management/adls_management/folder_management.py
adls_management/batch_process_phases/__init__.py
adls_management/batch_process_phases/from_to_phase.py
adls_management/interface_file_management/__init__.py
adls_management/interface_file_management/interface_file_handling.py
adls_management/utils/__init__.py
adls_management/utils/messages.py
adls_management/utils/settings.py
plugins/__init__.py
adls_management-0.1.20.dist-info/LICENSE
adls_management-0.1.20.dist-info/METADATA
adls_management-0.1.20.dist-info/WHEEL
adls_management-0.1.20.dist-info/top_level.txt
adls_management-0.1.20.dist-info/RECORD
