Metadata-Version: 2.1
Name: adls-management
Version: 0.1.20
Summary: metadata lake file management
Home-page: https://github.com/jacbeekers/metalake-file-management
Author: Jac. Beekers
Author-email: beekersjac@gmail.com
License: UNKNOWN
Platform: UNKNOWN
Classifier: Programming Language :: Python :: 3
Classifier: License :: OSI Approved :: MIT License
Classifier: Operating System :: OS Independent
Requires-Python: >=3.6
Requires-Dist: jsonschema
Requires-Dist: azure-storage-file-datalake
